a_share_code_converter/__init__.py
a_share_code_converter/converter.py
a_share_code_converter-0.2.2.dist-info/LICENSE
a_share_code_converter-0.2.2.dist-info/METADATA
a_share_code_converter-0.2.2.dist-info/WHEEL
a_share_code_converter-0.2.2.dist-info/top_level.txt
a_share_code_converter-0.2.2.dist-info/RECORD
