Metadata-Version: 2.1
Name: a-share-code-converter
Version: 0.2.2
Summary: A lightweight Python utility to convert A-share stock codes to various formats
Home-page: https://github.com/xTbwOw/a_share_code_converter
Author: xTbwOw
Author-email: xTbwOw <tomtang0619@gmail.com>
License: MIT License
Classifier: Programming Language :: Python :: 3
Classifier: Operating System :: OS Independent
Classifier: License :: OSI Approved :: MIT License
Classifier: Intended Audience :: Developers
Classifier: Topic :: Software Development :: Libraries
Requires-Python: >=3.7
License-File: LICENSE
Requires-Dist: numpy >=1.20
Requires-Dist: pandas >=1.3
Requires-Dist: polars >=0.18
